LICENSE.txt
MANIFEST.in
README.md
setup.cfg
setup.py
Examples/README.md
Examples/example1/FORCE_SETS
Examples/example1/README
Examples/example1/band.conf
Examples/example1/band.yaml
Examples/example1/phonopy.freq.gp
Examples/example1/phonopy.yaml
Examples/example1/phonopy_disp.yaml
Examples/example2/README
Examples/example2/ZrN.dyn0
Examples/example2/ZrN.dyn1
Examples/example2/ZrN.dyn2
Examples/example2/ZrN.dyn3
Examples/example2/ZrN.fc
Examples/example2/ZrN.freq
Examples/example2/ZrN.freq.gp
Examples/example2/matdyn.in
Examples/example2/ph.in
Examples/example2/ph.out
Examples/example2/q2r.in
Examples/example2/scf.in
Examples/example2/scf.out
Examples/example3/README
Examples/example3/ZrN.a2f
Examples/example3/ZrN.a2f.01
Examples/example3/ZrN.a2f_iso
Examples/example3/ZrN.a2f_tr.01
Examples/example3/ZrN.kmap
Examples/example3/ZrN.lambda_FS
Examples/example3/ZrN.lambda_k_pairs
Examples/example3/ZrN.nnkp
Examples/example3/ZrN.phdos
Examples/example3/ZrN.phdos.01
Examples/example3/ZrN.phdos_proj
Examples/example3/ZrN.res.01
Examples/example3/ZrN.win
Examples/example3/epw.in
Examples/example3/nscf.in
Examples/example3/nscf.out
Examples/example3/scf.in
Examples/example3/scf.out
Examples/example4/README
Examples/example4/freq.txt
Examples/example4/tmp/ZrN.egnv
Examples/example4/tmp/ZrN.ephmat1
Examples/example4/tmp/ZrN.freq
Examples/example4/tmp/ZrN.ikmap
elphtk/__init__.py
elphtk/arguments.py
elphtk/epw_binary.py
elphtk/epw_tool.py
elphtk/phonon_plot.py
elphtk/phonopy_phonon.py
elphtk/pkg_info.py
elphtk/qe_phonon.py
elphtk/wgauss.py
elphtk.egg-info/PKG-INFO
elphtk.egg-info/SOURCES.txt
elphtk.egg-info/dependency_links.txt
elphtk.egg-info/requires.txt
elphtk.egg-info/top_level.txt
scripts/phplot
scripts/post_epw
scripts/qe2epw
scripts/qe_lambda