Metadata-Version: 2.1
Name: elphtk
Version: 0.0.4
Summary: Python library for (electron)-phonon-related analysis
Author: Shunhong Zhang
Author-email: zhangshunhong.pku@gmail.com
License: MIT License
Keywords: [Python,Phonon,Electron-phonon]
Platform: [Linux]
License-File: LICENSE.txt
